fileoperator/__init__.py
fileoperator/compression.py
fileoperator/encryption.py
fileoperator/file_operations.py
fileoperator/hash.py
fileoperator-0.1.1.dist-info/LICENSE.txt
fileoperator-0.1.1.dist-info/METADATA
fileoperator-0.1.1.dist-info/WHEEL
fileoperator-0.1.1.dist-info/top_level.txt
fileoperator-0.1.1.dist-info/RECORD
