Metadata-Version: 2.1
Name: fileoperator
Version: 0.1.1
Summary: An all-in-one utility package for file operations.
Home-page: https://github.com/michaelsousajr/fileoperator
Author: Michael Sousa
Author-email: ms22dq@fsu.com
Classifier: Development Status :: 3 - Alpha
Classifier: Intended Audience :: Developers
Classifier: License :: OSI Approved :: MIT License
Classifier: Programming Language :: Python :: 3
Classifier: Programming Language :: Python :: 3.7
Classifier: Programming Language :: Python :: 3.8
Classifier: Programming Language :: Python :: 3.9
Classifier: Programming Language :: Python :: 3.10
Classifier: Operating System :: OS Independent
Requires-Python: >=3.7
License-File: LICENSE.txt
Requires-Dist: cryptography
Requires-Dist: pyperclip
